mathena/__init__.py
mathena/basic/__init__.py
mathena/basic/misc.py
mathena/basic/primefactorization.py
mathena/shapes/__init__.py
mathena/shapes/triangle.py
mathena-1.0.dist-info/METADATA
mathena-1.0.dist-info/WHEEL
mathena-1.0.dist-info/top_level.txt
mathena-1.0.dist-info/RECORD
